{"chunk_definitions":[{"row":20,"row_count":1,"visible":true,"expansion_state":0,"options":{"engine":"r","label":"setup","include":false},"document_id":"A8250CA1","chunk_id":"csetup_chunk","chunk_label":"setup"},{"row":80,"row_count":1,"visible":true,"expansion_state":0,"options":{"engine":"r","label":"unnamed-chunk-61"},"document_id":"A8250CA1","chunk_id":"c2krge9x21tu7","chunk_label":"unnamed-chunk-1"},{"row":98,"row_count":1,"visible":true,"expansion_state":0,"options":{"engine":"r","label":"unnamed-chunk-62"},"document_id":"A8250CA1","chunk_id":"c27ngew85uz6y","chunk_label":"unnamed-chunk-2"},{"row":126,"row_count":1,"visible":true,"expansion_state":0,"options":{"engine":"r","label":"unnamed-chunk-63"},"document_id":"A8250CA1","chunk_id":"cnx764kvvi0g0","chunk_label":"unnamed-chunk-3"},{"row":207,"row_count":1,"visible":true,"expansion_state":0,"options":{"engine":"r","include":false,"label":"unnamed-chunk-71"},"document_id":"A8250CA1","chunk_id":"cm5zsz8k8r6yv","chunk_label":"unnamed-chunk-4"},{"row":242,"row_count":1,"visible":true,"expansion_state":0,"options":{"engine":"r","include":false,"label":"unnamed-chunk-59"},"document_id":"A8250CA1","chunk_id":"cdrwq7i03yca3","chunk_label":"unnamed-chunk-5"},{"row":254,"row_count":1,"visible":true,"expansion_state":0,"options":{"engine":"r","include":false,"label":"unnamed-chunk-60"},"document_id":"A8250CA1","chunk_id":"c7yfmjxrptvcs","chunk_label":"unnamed-chunk-6"}],"doc_write_time":1746557573,"working_dir":null,"default_chunk_options":{},"chunk_rendered_width":700}